{"cameraMode":{"drawMode":0,"name":"Shaded","section":"Shading Mode"},"sceneLighting":true,"audioPlay":false,"sceneViewState":{"m_AlwaysRefresh":false,"showFog":true,"showSkybox":true,"showFlares":true,"showImageEffects":true,"showParticleSystems":true,"showVisualEffectGraphs":true,"m_FxEnabled":true},"in2DMode":false,"pivot":{"x":-33.727115631103519,"y":-11.615161895751954,"z":-6.998283863067627},"rotation":{"x":-0.11160054057836533,"y":0.7660864591598511,"z":-0.13848739862442017,"w":-0.6177344918251038},"size":20.537057876586915,"orthographic":false}